finmarketpy/__init__.py
finmarketpy/backtest/__init__.py
finmarketpy/backtest/backtestcomparison.py
finmarketpy/backtest/backtestengine.py
finmarketpy/backtest/backtestrequest.py
finmarketpy/backtest/tradeanalysis.py
finmarketpy/curve/__init__.py
finmarketpy/curve/abstractcurve.py
finmarketpy/curve/abstractpricer.py
finmarketpy/curve/fxforwardscurve.py
finmarketpy/curve/fxoptionscurve.py
finmarketpy/curve/fxspotcurve.py
finmarketpy/curve/rates/__init__.py
finmarketpy/curve/rates/fxforwardspricer.py
finmarketpy/curve/volatility/__init__.py
finmarketpy/curve/volatility/abstractvolsurface.py
finmarketpy/curve/volatility/fxoptionspricer.py
finmarketpy/curve/volatility/fxvolsurface.py
finmarketpy/curve/volatility/volstats.py
finmarketpy/economics/__init__.py
finmarketpy/economics/eventstudy.py
finmarketpy/economics/marketliquidity.py
finmarketpy/economics/quickchart.py
finmarketpy/economics/report.py
finmarketpy/economics/seasonality.py
finmarketpy/economics/techindicator.py
finmarketpy/network_analysis/__init__.py
finmarketpy/network_analysis/learn_network_structure.py
finmarketpy/network_analysis/plot_network_structure.py
finmarketpy/util/__init__.py
finmarketpy/util/marketconstants.py
finmarketpy/util/marketutil.py
finmarketpy_examples/__init__.py
finmarketpy_examples/backtest_example.py
finmarketpy_examples/boe-rate.png
finmarketpy_examples/events_examples.py
finmarketpy_examples/fx_forwards_asian_indices_examples.py
finmarketpy_examples/fx_forwards_indices_examples.py
finmarketpy_examples/fx_forwards_pricing_examples.py
finmarketpy_examples/fx_options_indices_examples.py
finmarketpy_examples/fx_options_pricing_examples.py
finmarketpy_examples/fx_spot_indices_examples.py
finmarketpy_examples/fx_vol_surface_animation.py
finmarketpy_examples/fx_vol_surface_interpolation_examples.py
finmarketpy_examples/gold seasonality.png
finmarketpy_examples/quandl_examples.py
finmarketpy_examples/quickchart_examples.py
finmarketpy_examples/returns_examples.py
finmarketpy-0.11.19.dist-info/LICENCE
finmarketpy-0.11.19.dist-info/METADATA
finmarketpy-0.11.19.dist-info/WHEEL
finmarketpy-0.11.19.dist-info/top_level.txt
finmarketpy-0.11.19.dist-info/RECORD
