Metadata-Version: 2.1
Name: finmarketpy
Version: 0.11.19
Summary: finmarketpy is a Python based library for backtesting trading strategies
Home-page: https://github.com/cuemacro/finmarketpy
Author: Saeed Amen
Author-email: Saeed Amen <saeed@cuemacro.com>
License: Apache 2.0
Project-URL: repository, https://github.com/cuemacro/finmarketpy
Keywords: trading,markets,currencies,pandas,data,Bloomberg,tick,stocks,equities
Requires-Python: >=3.9
License-File: LICENCE
Requires-Dist: blosc
Requires-Dist: chartpy
Requires-Dist: findatapy
Requires-Dist: matplotlib
Requires-Dist: numba
Requires-Dist: numpy <2
Requires-Dist: pandas >=1.5.3
Requires-Dist: scikit-learn
Requires-Dist: seasonal
